{
  "code": "163208",
  "generatedAt": "2026-03-16T06:06:38.185Z",
  "splitMode": "year-split",
  "method": "history-holdings-daily-return",
  "explanation": "旧版离线研究主要基于净值时序特征，并未直接按前十大持仓逐日涨跌幅估值；本版已切换为历史前十大持仓逐日估值。",
  "fallbackMode": "none",
  "disclosureCount": 47,
  "usedQuoteTickers": [
    "XOM",
    "CVX",
    "COP",
    "SHEL",
    "OXY",
    "XOP",
    "XLE",
    "IXC"
  ],
  "avgHoldingCoverage": 0.9212410501193318,
  "trainRange": "2025-01-02 ~ 2025-12-31",
  "validationRange": "2026-01-05 ~ 2026-03-12",
  "segmented": {
    "maeTrain": 0.0034017433741817386,
    "maeValidation": 0.003697304703117566,
    "maeValidation30": 0.004241783806665134,
    "maeValidation30Robust": 0.0037532528650804785,
    "maeValidationWeighted": 0.003697304703117566,
    "maeValidation30Weighted": 0.004241783806665134
  },
  "dualObjective": {
    "mode": "holdings-return-plus-fx",
    "lambda": 0.1,
    "maeValidation": 0.010243485355799338,
    "maeValidation30": 0.010426561686876978,
    "premiumProxyValidation": 0.013871784900157051
  },
  "adaptiveModel": {
    "kLearnRate": 0.12,
    "biasLearnRate": 0.12,
    "fxMix": 0.5,
    "tradingShockThreshold": 0.015571102619668467,
    "offShockThreshold": 0.015779995856770323,
    "shockBaseBlend": 0.45,
    "tradingBaseBlend": 0.5900000000000001,
    "offBaseBlend": 0.65,
    "sessionSplit": true,
    "tradingLeadScale": 1.08,
    "offLeadScale": 1.14,
    "upMoveScale": 1.12,
    "downMoveScale": 0.9,
    "shockAmplify": 0.2,
    "arWeight": 0,
    "gapBranch": true,
    "gapCoef": 0.55,
    "gapAmplify": 0.35,
    "gapSignalThreshold": 0.006,
    "weekendThreshold": 0.01,
    "weekendAmplify": 0.35,
    "weekendFxCoef": 0.4,
    "weekendMomentumCoef": 0,
    "extremeThreshold": 0.02291797719077037,
    "extremeAmplify": 0,
    "tuningMae": 0.0026326363015692885,
    "tuningMae30": 0.0023027608646301713,
    "tuningMae30Robust": 0.0020448820598813265,
    "validationSelectionMae": 0.003930784525893507,
    "validationSelectionMae30": 0.004435792921065496,
    "validationSelectionMae30Robust": 0.003954400671107807,
    "validationSelectionTrainTop4": 0.014071803584586678,
    "refinedSelectionMae": 0.0036951474776689285,
    "refinedSelectionMae30": 0.00423393635527215,
    "refinedSelectionMae30Robust": 0.0037457705842326287,
    "refinedSelectionTrainTop4": 0.014030631961043705,
    "residualRefineShrink": 0.2,
    "residualRefineCap": 0.008,
    "residualRefineMae": 0.003697304703117566,
    "residualRefineMae30": 0.004241783806665134,
    "residualRefineMae30Robust": 0.0037532528650804785,
    "residualRefineTrainTop4": 0.013964253548837069,
    "residualRefineTrainTop8": 0.01209133817847377
  },
  "validationDiagnostics": {
    "maeBySession": {
      "oilTradingSession": 0.0036558883353559842,
      "nonTradingSession": 0.003853766536883543,
      "gapDayHint": 0.003853766536883543,
      "nonGapDay": 0.0036558883353559842
    },
    "topErrorDays": [
      {
        "date": "2026-03-06",
        "absError": 0.018409181112620132,
        "predictedReturn": 0.004381958797495155,
        "targetReturn": 0.023218574859887875,
        "residualCorrection": -0.00001886548728911555,
        "isOilTradingSession": true,
        "isGapDayHint": false,
        "isAnomalyDay": false,
        "gapSignal": 0.0041781432506865085,
        "usoReturn": 0.001892320839946393,
        "bnoReturn": 0.0015934844192635467,
        "fxReturn": 0.0034031417409985387,
        "tags": []
      },
      {
        "date": "2026-03-09",
        "absError": 0.014019136804251042,
        "predictedReturn": 0.003704388151312497,
        "targetReturn": -0.010172143974961023,
        "residualCorrection": -0.00009684801843222529,
        "isOilTradingSession": false,
        "isGapDayHint": true,
        "isAnomalyDay": false,
        "gapSignal": 0.003716440512161404,
        "usoReturn": -0.01407420946810456,
        "bnoReturn": -0.004419303517765649,
        "fxReturn": 0.000991746529248605,
        "tags": [
          "非油价交易时段",
          "缺口日"
        ]
      },
      {
        "date": "2026-03-12",
        "absError": 0.010615505182713814,
        "predictedReturn": 0.017894795680400907,
        "targetReturn": 0.028816199376946905,
        "residualCorrection": -0.00001859238610732105,
        "isOilTradingSession": true,
        "isGapDayHint": false,
        "isAnomalyDay": false,
        "gapSignal": 0.007065158399375817,
        "usoReturn": 0.012265468455886941,
        "bnoReturn": 0.009301509301509414,
        "fxReturn": -0.0006299208016432578,
        "tags": []
      },
      {
        "date": "2026-03-05",
        "absError": 0.007322197328873514,
        "predictedReturn": 0.0031185886215509802,
        "targetReturn": 0.01051779935275099,
        "residualCorrection": -0.000016826309801600475,
        "isOilTradingSession": true,
        "isGapDayHint": false,
        "isAnomalyDay": false,
        "gapSignal": 0.000060116057477230364,
        "usoReturn": 0.018971201094731605,
        "bnoReturn": 0.005161060686954988,
        "fxReturn": -0.0019386073878460142,
        "tags": []
      },
      {
        "date": "2026-02-02",
        "absError": 0.00678360606189321,
        "predictedReturn": -0.01909984123915929,
        "targetReturn": -0.01240035429583708,
        "residualCorrection": -0.00009675608447299101,
        "isOilTradingSession": false,
        "isGapDayHint": true,
        "isAnomalyDay": false,
        "gapSignal": -0.0018015693414845592,
        "usoReturn": -0.03194523673702232,
        "bnoReturn": -0.019588638589618013,
        "fxReturn": -0.001369260110518855,
        "tags": [
          "非油价交易时段",
          "缺口日"
        ]
      },
      {
        "date": "2026-01-21",
        "absError": 0.006015140431629207,
        "predictedReturn": 0.012477601141735784,
        "targetReturn": 0.018604651162790642,
        "residualCorrection": -0.000016825453384830265,
        "isOilTradingSession": true,
        "isGapDayHint": false,
        "isAnomalyDay": false,
        "gapSignal": -0.002320825526309699,
        "usoReturn": 0.03753082614056713,
        "bnoReturn": 0.024159663865546133,
        "fxReturn": 0.0010326804529987577,
        "tags": []
      },
      {
        "date": "2026-02-25",
        "absError": 0.005987430990328502,
        "predictedReturn": -0.0008040453370323402,
        "targetReturn": -0.006751054852320637,
        "residualCorrection": -0.000019013995836554896,
        "isOilTradingSession": true,
        "isGapDayHint": false,
        "isAnomalyDay": false,
        "gapSignal": 0.00016837854304500226,
        "usoReturn": -0.007822947312115636,
        "bnoReturn": -0.004174228675136171,
        "fxReturn": -0.0012217648684420546,
        "tags": []
      },
      {
        "date": "2026-02-12",
        "absError": 0.005832679559757192,
        "predictedReturn": -0.009615262617781832,
        "targetReturn": -0.015358361774744034,
        "residualCorrection": -0.00001979414863697672,
        "isOilTradingSession": true,
        "isGapDayHint": false,
        "isAnomalyDay": false,
        "gapSignal": -0.0031281384507314295,
        "usoReturn": -0.029719576009660575,
        "bnoReturn": -0.01818843215714805,
        "fxReturn": -0.001761572532785305,
        "tags": []
      },
      {
        "date": "2026-01-13",
        "absError": 0.005433767932532141,
        "predictedReturn": 0.007776789229654372,
        "targetReturn": 0.013282732447817747,
        "residualCorrection": -0.00001824626503855499,
        "isOilTradingSession": true,
        "isGapDayHint": false,
        "isAnomalyDay": false,
        "gapSignal": 0.00048390002977716836,
        "usoReturn": 0.01732789713031191,
        "bnoReturn": 0.014242555028053383,
        "fxReturn": 0.000691731654042238,
        "tags": []
      },
      {
        "date": "2026-01-30",
        "absError": 0.005207945352977861,
        "predictedReturn": 0.00431838079956843,
        "targetReturn": -0.0008849557522122575,
        "residualCorrection": -0.000018835276426137915,
        "isOilTradingSession": true,
        "isGapDayHint": false,
        "isAnomalyDay": false,
        "gapSignal": 0.00021653497940918125,
        "usoReturn": 0.009138663020795912,
        "bnoReturn": 0.010690952286675826,
        "fxReturn": 0.0018328688720652409,
        "tags": []
      }
    ]
  },
  "trainDiagnostics": {
    "topErrorDays": [
      {
        "date": "2025-04-21",
        "absError": 0.018456242510184406,
        "predictedReturn": 0.0008015297472775897,
        "targetReturn": -0.017334777898158182,
        "residualCorrection": -0.0000927692997973264,
        "isOilTradingSession": false,
        "isGapDayHint": true,
        "isAnomalyDay": false,
        "gapSignal": 0,
        "usoReturn": 0,
        "bnoReturn": 0,
        "fxReturn": 0,
        "tags": [
          "非油价交易时段",
          "缺口日",
          "披露覆盖不足"
        ]
      },
      {
        "date": "2025-01-27",
        "absError": 0.01418628550696499,
        "predictedReturn": 0.0062318832676947185,
        "targetReturn": -0.007843137254901933,
        "residualCorrection": -0.00009741972613198108,
        "isOilTradingSession": false,
        "isGapDayHint": true,
        "isAnomalyDay": false,
        "gapSignal": 0.008326672491457816,
        "usoReturn": -0.01925536450191845,
        "bnoReturn": -0.010405372676220104,
        "fxReturn": 0.0027289613788437084,
        "tags": [
          "非油价交易时段",
          "缺口日"
        ]
      },
      {
        "date": "2025-04-10",
        "absError": 0.01168279364554281,
        "predictedReturn": -0.05250459129931397,
        "targetReturn": -0.04130434782608694,
        "residualCorrection": -0.00002022134598992159,
        "isOilTradingSession": true,
        "isGapDayHint": false,
        "isAnomalyDay": false,
        "gapSignal": -0.006128464127042082,
        "usoReturn": -0.08220502901353965,
        "bnoReturn": -0.06532170310037178,
        "fxReturn": -0.0042324888226528135,
        "tags": []
      },
      {
        "date": "2025-07-07",
        "absError": 0.011531692532656068,
        "predictedReturn": 0.0005040923167402932,
        "targetReturn": -0.01090188305252715,
        "residualCorrection": -0.00009298567112660308,
        "isOilTradingSession": false,
        "isGapDayHint": true,
        "isAnomalyDay": false,
        "gapSignal": 0.000558897729477934,
        "usoReturn": 0,
        "bnoReturn": 0,
        "fxReturn": 0.0017465554046185439,
        "tags": [
          "非油价交易时段",
          "缺口日",
          "披露覆盖不足"
        ]
      },
      {
        "date": "2025-07-02",
        "absError": 0.011407940026008978,
        "predictedReturn": 0.010694727981539743,
        "targetReturn": 0.022357723577235866,
        "residualCorrection": -0.000018505260116712322,
        "isOilTradingSession": true,
        "isGapDayHint": false,
        "isAnomalyDay": false,
        "gapSignal": 0.001733002310208967,
        "usoReturn": 0.018915510718789497,
        "bnoReturn": 0.01720046178931467,
        "fxReturn": 0.00146845134968987,
        "tags": []
      },
      {
        "date": "2025-04-03",
        "absError": 0.009905365690862977,
        "predictedReturn": -0.04755308809482743,
        "targetReturn": -0.05689488910318219,
        "residualCorrection": -0.0007414065362335035,
        "isOilTradingSession": true,
        "isGapDayHint": true,
        "isAnomalyDay": false,
        "gapSignal": 0.0033939488350190608,
        "usoReturn": -0.1068411214953271,
        "bnoReturn": -0.07850950676377855,
        "fxReturn": 0.004968766575151218,
        "tags": [
          "缺口日",
          "主代理/次代理分化大"
        ]
      },
      {
        "date": "2025-11-28",
        "absError": 0.00987789704166775,
        "predictedReturn": -0.0003848759203030805,
        "targetReturn": 0.009587727708533,
        "residualCorrection": -0.000018537714077516663,
        "isOilTradingSession": true,
        "isGapDayHint": false,
        "isAnomalyDay": false,
        "gapSignal": -0.0003408068455168234,
        "usoReturn": 0,
        "bnoReturn": 0,
        "fxReturn": -0.001065021392240073,
        "tags": [
          "披露覆盖不足"
        ]
      },
      {
        "date": "2025-10-20",
        "absError": 0.009682488473902184,
        "predictedReturn": 0.00019106597800307412,
        "targetReturn": 0.009970089730807485,
        "residualCorrection": -0.0000912575966609711,
        "isOilTradingSession": false,
        "isGapDayHint": true,
        "isAnomalyDay": false,
        "gapSignal": -0.0023363394727361378,
        "usoReturn": 0.013757384478433332,
        "bnoReturn": 0.010584939920143865,
        "fxReturn": -0.00025955477237038505,
        "tags": [
          "非油价交易时段",
          "缺口日"
        ]
      },
      {
        "date": "2025-04-09",
        "absError": 0.009334223487807325,
        "predictedReturn": 0.06857017906649347,
        "targetReturn": 0.05868814729574234,
        "residualCorrection": -0.0007174976385543578,
        "isOilTradingSession": true,
        "isGapDayHint": true,
        "isAnomalyDay": false,
        "gapSignal": 0.002830335828423962,
        "usoReturn": 0.11608281817289767,
        "bnoReturn": 0.07744170073940526,
        "fxReturn": 0.0028069355491731063,
        "tags": [
          "缺口日",
          "主代理/次代理分化大"
        ]
      },
      {
        "date": "2025-12-16",
        "absError": 0.009216145123592812,
        "predictedReturn": -0.016934369193429433,
        "targetReturn": -0.02591170825335909,
        "residualCorrection": -0.00001952131743440954,
        "isOilTradingSession": true,
        "isGapDayHint": false,
        "isAnomalyDay": false,
        "gapSignal": 0.0010140591171603343,
        "usoReturn": -0.037881121034801346,
        "bnoReturn": -0.03053695768612741,
        "fxReturn": -0.0010930466617361523,
        "tags": []
      }
    ]
  },
  "chartPath": "generated/163208-offline-research.svg",
  "notes": "估值点使用同日持仓涨跌幅对齐同日净值，不做时间平移；163208 使用“全球油气交易时段/非交易时段”分参数与“主代理/次代理跳空+汇率错位”缺口日专用分支。若个别持仓缺历史行情，按可用权重归一化。"
}
